LAOC2/LAOC2_NATAN/pratica4_GabrielQuezada_NatanRocha/pratica 4_GabrielQuezada_NatanRocha/SnoppingParte1/Snopping/Receptor.v
module Receptor (
    input wire [1:0] i_Message
);
  // States
  localparam [1:0] INVALID = 0;
  localparam [1:0] SHARED = 1;
  localparam [1:0] MODIFIED = 2;
  reg [1:0] r_State;

  // Actions
  localparam [1:0] WRITEBACK = 1;
  localparam [1:0] ABORT = 2;
  localparam [1:0] WRITEBACK_AND_ABORT = 3;
  reg [1:0] r_Signal = 0;

  // Messages
  localparam [1:0] READ_MISS = 1;
  localparam [1:0] WRITE_MISS = 2;
  localparam [1:0] INVALIDATE = 3;

  initial r_State <= SHARED;

  always @(i_Message) begin
    case (r_State)
      INVALID: begin
        r_Signal <= 0;
        r_State  <= INVALID;
      end
      MODIFIED: begin
        case (i_Message)
          READ_MISS: begin
            r_Signal <= WRITEBACK_AND_ABORT;
            r_State  <= SHARED;
          end
          WRITE_MISS: begin
            r_Signal <= WRITEBACK_AND_ABORT;
            r_State  <= INVALID;
          end
        endcase
      end
      SHARED: begin
        case (i_Message)
          READ_MISS: begin
            r_Signal <= 0;
            r_State  <= SHARED;
          end
          WRITE_MISS, INVALIDATE: begin
            r_Signal <= 0;
            r_State  <= INVALID;
          end
        endcase
      end
    endcase
  end

endmodule

LAOC2/LAOC2_NATAN/pratica4_GabrielQuezada_NatanRocha/pratica 4_GabrielQuezada_NatanRocha/SnoppingParte1/Snopping/Emissor.v
module Emissor (
    input wire i_Clock,
    input wire i_Start,
    input wire [1:0] i_Operation,

    output wire [1:0] o_Message
);
  // States
  localparam [1:0] INVALID = 0;
  localparam [1:0] SHARED = 1;
  localparam [1:0] MODIFIED = 2;
  reg [1:0] r_State;

  // Messages
  localparam [1:0] READ_MISS = 1;
  localparam [1:0] WRITE_MISS = 2;
  localparam [1:0] INVALIDATE = 3;
  reg [1:0] r_Message = 0;

  // Actions
  localparam [1:0] WRITEBACK = 1;
  localparam [1:0] ABORT = 2;
  reg [1:0] r_Action = 0;

  // Operations
  localparam [1:0] RM = 0;
  localparam [1:0] RH = 1;
  localparam [1:0] WM = 2;
  localparam [1:0] WH = 3;

  initial r_State <= INVALID;

  localparam STEP0 = 0;
  localparam STEP1 = 1;
  reg [1:0] r_Step = STEP0;

  always @(posedge i_Clock) begin

    case (r_Step)
      STEP0: begin
        if (i_Start) begin
          r_Step <= STEP1;
        end
      end
      STEP1: begin
        case (r_State)
          INVALID: begin
            case (i_Operation)
              RM, RH: begin
                r_Message <= READ_MISS;
                r_Action  <= 0;
                r_State   <= SHARED;
              end
              WM, WH: begin
                r_Message <= WRITE_MISS;
                r_Action  <= 0;
                r_State   <= MODIFIED;
              end
            endcase
          end
          MODIFIED: begin
            case (i_Operation)
              WH, RH: begin
                r_Message <= 0;
                r_Action  <= 0;
                r_State   <= MODIFIED;
              end
              WM: begin
                r_Message <= WRITE_MISS;
                r_Action  <= WRITEBACK;
                r_State   <= MODIFIED;
              end
              RM: begin
                r_Message <= READ_MISS;
                r_Action  <= WRITEBACK;
                r_State   <= SHARED;
              end
            endcase
          end
          SHARED: begin
            case (i_Operation)
              RH: begin
                r_Message <= 0;
                r_Action  <= 0;
                r_State   <= SHARED;
              end
              RM: begin
                r_Message <= READ_MISS;
                r_Action  <= 0;
                r_State   <= SHARED;
              end
              WH: begin
                r_Message <= INVALIDATE;
                r_Action  <= 0;
                r_State   <= MODIFIED;
              end
              WM: begin
                r_Message <= WRITE_MISS;
                r_Action  <= 0;
                r_State   <= MODIFIED;
              end
            endcase
          end
        endcase

        r_Step <= STEP0;
      end

    endcase


  end

  assign o_Message = r_Message;

endmodule

LAOC2/LAOC2_NATAN/pratica4_GabrielQuezada_NatanRocha/pratica 4_GabrielQuezada_NatanRocha/SnoppingParte1/Snopping/Snopping.v
module Snopping (
    input wire i_Start,
    input wire i_Clock,
    input wire [1:0] i_Operation
);

  wire [1:0] w_Message;
  Emissor u_Emissor (
      i_Clock,
      i_Start,
      i_Operation,
      w_Message
  );

  Receptor u_Receptor (w_Message);

endmodule

LAOC2/LAOC2_NATAN/pratica4_GabrielQuezada_NatanRocha/pratica 4_GabrielQuezada_NatanRocha/SnoppingParte1/Snopping/SnoppingTestbench.v
module SnoppingTestbench;

  localparam [1:0] RM = 0;
  localparam [1:0] RH = 1;
  localparam [1:0] WM = 2;
  localparam [1:0] WH = 3;

  reg r_Clock = 0;
  reg r_Start = 0;
  reg [1:0] r_Operation;

  Snopping u_Dut (
      r_Start,
      r_Clock,
      r_Operation
  );

  always #5 r_Clock <= ~r_Clock;

  initial begin
    $dumpfile("test.vcd");
    $dumpvars(0, SnoppingTestbench);
  end

  task automatic displayState();
    begin
      $display("Maquina EMISSORA");
      $display("Estado: %1d", u_Dut.u_Emissor.r_State);
      $display("Mensagem: %1d", u_Dut.u_Emissor.r_Message);
      $display("Acao: %1d", u_Dut.u_Emissor.r_Action);

      $display("Maquina RECEPTORA");
      $display("Estado: %1d", u_Dut.u_Receptor.r_State);
      $display("Sinal: %1d", u_Dut.u_Receptor.r_Signal);


      $display("----------------------------------------------");
    end
  endtask

  initial begin
    #5;
    displayState();

    @(negedge r_Clock);
    $display("Operacao: RM, move EMISSORA para SHARED e RECEPTORA para SHARED");
    r_Operation = RM;
    r_Start = 1;
    @(negedge r_Clock);
    r_Start = 0;
    #20;
    displayState();

    @(negedge r_Clock);
    $display("Operacao: WH, move EMISSORA para MODIFIED e RECEPTORA para INVALID");
    r_Operation = WH;
    r_Start = 1;
    @(negedge r_Clock);
    r_Start = 0;
    #20;
    displayState();

    @(negedge r_Clock);
    $display("Operacao: RM, move EMISSORA para SHARED, ATIVA WRITEBACK e RECEPTORA para INVALID");
    r_Operation = RM;
    r_Start = 1;
    @(negedge r_Clock);
    r_Start = 0;
    #20;
    displayState();

    @(negedge r_Clock);
    $display("Operacao: WM, move EMISSORA para MODIFIED e RECEPTORA para INVALID");
    r_Operation = WM;
    r_Start = 1;
    @(negedge r_Clock);
    r_Start = 0;
    #20;
    displayState();

    $display("Troca o estado da RECEPTORA para MODIFIED por meio do codigo");
    u_Dut.u_Receptor.r_State = 2;

    @(negedge r_Clock);
    $display(
        "Operacao: RM, move EMISSORA para SHARED, faz WRITEBACK e RECEPTORA para SHARED, ativando ABORT");
    r_Operation = RM;
    r_Start = 1;
    @(negedge r_Clock);
    r_Start = 0;
    #20;
    displayState();

    $display("Troca o estado da RECEPTORA para MODIFIED por meio do codigo");
    u_Dut.u_Receptor.r_State = 2;

    @(negedge r_Clock);
    $display(
        "Operacao: WM, move EMISSORA para MODIFIED e RECEPTORA para INVALID, ativando ABORT");
    r_Operation = WM;
    r_Start = 1;
    @(negedge r_Clock);
    r_Start = 0;
    #20;
    displayState();


    #10;
    $finish();
  end

endmodule

LAOC2/LAOC2_NATAN/pratica4_GabrielQuezada_NatanRocha/pratica 4_GabrielQuezada_NatanRocha/SnoppingParte1/Snopping/simulation/modelsim/test.vcd
$date
	Tue Sep 10 19:48:15 2024
$end
$version
	ModelSim Version 10.1d
$end
$timescale
	1ps
$end
$scope module SnoppingTestbench $end
$var parameter 2 ! RM $end
$var parameter 2 " RH $end
$var parameter 2 # WM $end
$var parameter 2 $ WH $end
$var reg 1 % r_Clock $end
$var reg 1 & r_Start $end
$var reg 2 ' r_Operation [1:0] $end
$scope task displayState $end
$upscope $end
$scope module u_Dut $end
$var wire 1 ( i_Start $end
$var wire 1 ) i_Clock $end
$var wire 1 * i_Operation [1] $end
$var wire 1 + i_Operation [0] $end
$var wire 1 , w_Message [1] $end
$var wire 1 - w_Message [0] $end
$scope module u_Emissor $end
$var parameter 2 . INVALID $end
$var parameter 2 / SHARED $end
$var parameter 2 0 MODIFIED $end
$var parameter 2 1 READ_MISS $end
$var parameter 2 2 WRITE_MISS $end
$var parameter 2 3 INVALIDATE $end
$var parameter 2 4 WRITEBACK $end
$var parameter 2 5 ABORT $end
$var parameter 2 6 RM $end
$var parameter 2 7 RH $end
$var parameter 2 8 WM $end
$var parameter 2 9 WH $end
$var parameter 32 : STEP0 $end
$var parameter 32 ; STEP1 $end
$var wire 1 ) i_Clock $end
$var wire 1 ( i_Start $end
$var wire 1 * i_Operation [1] $end
$var wire 1 + i_Operation [0] $end
$var wire 1 , o_Message [1] $end
$var wire 1 - o_Message [0] $end
$var reg 2 < r_State [1:0] $end
$var reg 2 = r_Message [1:0] $end
$var reg 2 > r_Action [1:0] $end
$var reg 2 ? r_Step [1:0] $end
$upscope $end
$scope module u_Receptor $end
$var parameter 2 @ INVALID $end
$var parameter 2 A SHARED $end
$var parameter 2 B MODIFIED $end
$var parameter 2 C WRITEBACK $end
$var parameter 2 D ABORT $end
$var parameter 2 E WRITEBACK_AND_ABORT $end
$var parameter 2 F READ_MISS $end
$var parameter 2 G WRITE_MISS $end
$var parameter 2 H INVALIDATE $end
$var wire 1 , i_Message [1] $end
$var wire 1 - i_Message [0] $end
$var reg 2 I r_State [1:0] $end
$var reg 2 J r_Signal [1:0] $end
$upscope $end
$upscope $end
$upscope $end
$enddefinitions $end
#0
$dumpvars
0%
0&
bx '
b0 <
b0 =
b0 >
b0 ?
b1 I
b0 J
b0 !
b1 "
b10 #
b11 $
b0 .
b1 /
b10 0
b1 1
b10 2
b11 3
b1 4
b10 5
b0 6
b1 7
b10 8
b11 9
b0 :
b1 ;
b0 @
b1 A
b10 B
b1 C
b10 D
b11 E
b1 F
b10 G
b11 H
0-
0,
x+
x*
0)
0(
$end
#5
1%
1)
#10
0%
0)
b0 '
1&
0+
0*
1(
#15
1%
1)
b1 ?
#20
0%
0)
0&
0(
#25
1%
1)
b1 =
b1 <
b0 ?
1-
#30
0%
0)
#35
1%
1)
#40
0%
0)
b11 '
1&
1+
1*
1(
#45
1%
1)
b1 ?
#50
0%
0)
0&
0(
#55
1%
1)
b11 =
b10 <
b0 ?
1,
b0 I
#60
0%
0)
#65
1%
1)
#70
0%
0)
b0 '
1&
0+
0*
1(
#75
1%
1)
b1 ?
#80
0%
0)
0&
0(
#85
1%
1)
b1 =
b1 >
b1 <
b0 ?
0,
#90
0%
0)
#95
1%
1)
#100
0%
0)
b10 '
1&
1*
1(
#105
1%
1)
b1 ?
#110
0%
0)
0&
0(
#115
1%
1)
b10 =
b0 >
b10 <
b0 ?
0-
1,
#120
0%
0)
#125
1%
1)
#130
b10 I
0%
0)
b0 '
1&
0*
1(
#135
1%
1)
b1 ?
#140
0%
0)
0&
0(
#145
1%
1)
b1 =
b1 >
b1 <
b0 ?
1-
0,
b11 J
b1 I
#150
0%
0)
#155
1%
1)
#160
b10 I
0%
0)
b10 '
1&
1*
1(
#165
1%
1)
b1 ?
#170
0%
0)
0&
0(
#175
1%
1)
b10 =
b0 >
b10 <
b0 ?
0-
1,
b0 I
